<Language xmlns:xsi="http://www.w3.org/2001/XMLSchema-instance" xmlns:xsd="http://www.w3.org/2001/XMLSchema">
  <Code>CS</Code>
  <HelpPage>
    <!--
    ~~~~~~~~~~~~~~~~~~~~~~~~~
    |                 MASTER PAGES            |
    ~~~~~~~~~~~~~~~~~~~~~~~~~
    -->
    <!--LEAVE THIS ALONE NEEDED FOR THOSE PAGES-->
    <StationpediaPage>
      <Key>CartridgePage</Key>
      <Title>Kazety</Title>
      <Text>Lze je přidat do {THING:ItemTablet} nebo {THING:ItemAdvancedTablet} a provádět tak různé diagnostické funkce.
{LIST_OF_CARTRIDGES}</Text>
    </StationpediaPage>
    <StationpediaPage>
      <Key>FabricatorPage</Key>
      <Title>Konstruktéři</Title>
      <Text>Jedná se o poháněné struktury, které lze použít k výrobě věcí, které ve hře potřebujete. Obvykle odebírají {LINK:IngotPage;ingoty}, které poskytují {LINK:ReagentPage;činidla}, které potřebují k výrobě věcí.
        {LIST_OF_FABRICATORS}
      </Text>
    </StationpediaPage>
    <StationpediaPage>
      <Key>DevicePage</Key>
      <Title>Zařízení</Title>
      <Text>Tohle jsou struktury, obvykle napájené, které mají specializované funkce, včetně logiky, atmosféry a další. Jsou konstruovány stejným způsobem jako ostatní struktury.
        {LIST_OF_DEVICES}
      </Text>
    </StationpediaPage>
    <StationpediaPage>
      <Key>ImportExportPage</Key>
      <Title>Import / Export a dopravníky</Title>
      <Text>Tohle jsou struktury, obvykle napájené, které mají specializované funkce včetně logiky, atmosféry a další. Jsou konstruovány stejným způsobem jako ostatní struktury.
        {LIST_OF_DEVICES}
      </Text>
    </StationpediaPage>
    <StationpediaPage>
      <Key>SmeltingPage</Key>
      <Title>Tavení</Title>
      <Text>Jakmile budete mít {LINK:OrePage;rudy}, musíte je přeměnit na {LINK:IngotPage;ingoty}, aby jste mohli použít jejich {LINK:ReagentPage;činidla}. Tavením často vznikají {LINK:GasPage;plyny}. K tomu dochází buď v {THING:StructureArcFurnace} (pro jednoduché recepty) a v {THING:StructureFurnace} pro složitější {LINK:AlloyPage;slitiny}, a nakonec v {THING:StructureAdvancedFurnace} pro velmi složité {LINK:SuperAlloyPage;Superslitiny}. U složitých slitin budete muset dosáhnout směsí v perfektních poměrech, {LINK:TemperaturePage;teplota} a {LINK:PressurePage;tlak}.
      </Text>
    </StationpediaPage>
    <StationpediaPage>
      <Key>MiningPage</Key>
      <Title>Těžení</Title>
      <Text>Můžete těžit {LINK:OrePage;rudy} pomocí {THING:ItemMiningDrill}. Pokud nosíte {THING:ItemMiningBelt}, budou {LINK:OrePage;rudy} automaticky umístěny do něj.
      </Text>
    </StationpediaPage>
    <StationpediaPage>
      <Key>ConstructionPage</Key>
      <Title>Konstrukce</Title>
      <DisplayFilter>Guides</DisplayFilter>
      <Text>{HEADER:Začínáme}
Obvykle budete používat {LINK:KitPage;sady} k zahájení konstrukcí a poté dokončovat pomocí {LINK:ToolPage;nástrojů} a {LINK:ResourcePage;zdrojů}. Věnujte zvýšenou pozornost tomu, kolik sad je zapotřebí k vytvoření vybrané konstrukce, protože některé mohou vyžadovat více než jednu. U některých sad budete mít více druhů konstrukcí, které lze měnit pomocí {COLORRED:kolečka myši} na požadovanou variantu.

{HEADER:Fáze konstrukce}
Některé konstrukce mají více stupňů výstavby, a proto budou vyžadovat postupné dokončování. Popis vám poradí, co zrovna potřebujete k dokončení daného stupně. Někdy budete muset použít k dokončení stupně dva předměty, každý v jedné ruce. Některé nástroje bude nutné nejprve zapnout, což provedete držením v aktivní ruce a stisknutím klávesy {KEY:ToggleHandPower}.

{HEADER:Tipy}
Pohledem na neúplnou konstrukci získáte informace o tom, co všechno musíte udělat pro její dokončení. Pokud naopak chcete nějakou konstrukci rozebrat a držíte v ruce nesprávný {LINK:ToolPage;nástroj}, zobrazí se popisek se správným nástrojem.</Text>
    </StationpediaPage>
    <StationpediaPage>
      <Key>ReagentPage</Key>
      <Title>Činidla</Title>
      <Text>Tohle jsou chemická množství určitých typů.
      {LIST_OF_REAGENTS}
      </Text>
    </StationpediaPage>
    <StationpediaPage>
      <Key>GasPage</Key>
      <Title>Plyny</Title>
      <Text>Tohle jsou chemické plyny určitých typů.{LIST_OF_GASES}
      
      </Text>
    </StationpediaPage>
    <StationpediaPage>
      <Key>OrePage</Key>
      <Title>Rudy</Title>
      <Text>Jedná se o položky, které jsou {LINK:MiningPage;vytěžené} a často mohou být {LINK:SmeltingPage;taveny}. Můžete také získat smíšené rudy recyklací položek v {THING:StructureRecycler} a předáním přes {THING:StructureCentrifuge}, která je rozdělí na {LINK:OrePage;rudy} pro {LINK:SmeltingPage;tavení}.
        Existují některé rudy, které roztají, když jsou vystaveny slunečnímu záření nebo teplu a produkují {LINK:GasPage;plyny}. Například {THING:ItemIce} roztaje na {GAS:Water} a {GAS:Oxygen}. Dávejte pozor, abyste je chránili před teplem nebo slunečním zářením, dokud je opravdu nechcete roztát.
{LIST_OF_ORES}
      </Text>
    </StationpediaPage>
    <StationpediaPage>
      <Key>IngotPage</Key>
      <Title>Ingoty</Title>
      <Text>Jedná se o položky, které jsou obvykle vyrobeny z {LINK:SmeltingPage;tavení} {LINK:OrePage;rud}.

{LIST_OF_INGOTS}
      </Text>
    </StationpediaPage>
    <StationpediaPage>
      <Key>ToolPage</Key>
      <Title>Nástroje</Title>
      <Text>Toto jsou položky, které se vejdou do speciálního slotu a používají se pro {LINK:ConstructionPage;konstrukce} a další úkoly.

{LIST_OF_TOOLS}
      </Text>
    </StationpediaPage>
    <StationpediaPage>
      <Key>ResourcePage</Key>
      <Title>Zdroje</Title>
      <Text>Jedná se o položky, které jsou spotřebovány během {LINK:ConstructionPage;konstrukce} a dalších úkolu.
{LIST_OF_RESOURCES}
      </Text>
    </StationpediaPage>
    <StationpediaPage>
      <Key>KitPage</Key>
      <Title>Sady</Title>
      <Text>Jedná se o položky, které jsou spotřebovány během {LINK:ConstructionPage;konstrukce} a dalších úkolu.
{LIST_OF_KITS}
      </Text>
    </StationpediaPage>
    <StationpediaPage>
      <Key>FoodPage</Key>
      <Title>Jídlo</Title>
      <Text>Jedná se o položky, které se konzumují k zajištění výživy.
        {LIST_OF_FOOD}
      </Text>
    </StationpediaPage>
    <StationpediaPage>
      <Key>ClothingPage</Key>
      <Title>Oblečení</Title>
      <Text>Jedná se o položky, které mohou být nošeny entitami ve slotech.
{LIST_OF_CLOTHING}
      </Text>
    </StationpediaPage>
    <StationpediaPage>
      <Key>AppliancePage</Key>
      <Title>Spotřebiče</Title>
      <Text>Jedná se o předměty, které mohou být umístěny na pracovním stole pomocí hasáku.
{LIST_OF_APPLIANCES}</Text>
    </StationpediaPage>
    <StationpediaPage>
      <Key>RocketShuttleModulesHelpPage</Key>
      <Title>Raketoplán</Title>
      <DisplayFilter>Guides</DisplayFilter>
      <Text>{HEADER:Modulární raketový náklad}

{THING:StructureModularRocketCargo01} má kapacitu pro dvě bedny s deseti sloty. Na raketě můžete mít více nákladových modulů. Raketa může zvednout celkem až sedm modulů.

{HEADER:Raketový velitelský modul}

{THING:StructureModularRocketCommand01} musí být umístěna na vrcholu rakety. Posoudí připravenost rakety k letu. Jakmile jsou splněny všechny podmínky, může být raketa vypuštěna, když všichni hráči sedí v modulu stisknutím tlačítka &quot;Spuštění&quot; na konzoli.

Pro spuštění musí být splněny následující podmínky:

Palivo plné;
Poměr směsi paliva správný;
Všichni hráči sedící;
Napájení do odpalovací rampy;
Plně postavená raketa

Konzole {THING:StructureModularRocketCommand01} zobrazuje aktuální stav těchto podmínek. Nevyžaduje atmosféru pro zvednutí - atmosféra vašeho obleku je dostatečná.

{HEADER:Modulární raketový motor}

{THING:StructureModularRocketEngine01} je schopen zvednout až sedm modulů (včetně sebe).

{HEADER:Modulární raketová palivová nádrž}

{THING:StructureModularRocketFueltank01} vyžaduje směs 2 : 1 {GAS:Volatiles} a {GAS:Oxygen}. Pokud směs překročí tyto proporce nebo umístíte do nádrže jiné plyny, konzole {THING:StructureModularRocketCommand01} zobrazí chybu &quot;Neplatný&quot;.

          </Text>
    </StationpediaPage>
    <StationpediaPage>
      <Key>RocketShuttlePage</Key>
      <Title>Raketoplán</Title>
      <Text>Tyto raketové moduly se používají k cestování mezi světy a vyžadují {THING:StructureLaunchPad}.
{HEADER:Seznam raketových modulů}
{LIST_OF_ROCKET_SHUTTLE}</Text>
    </StationpediaPage>
    <StationpediaPage>
      <Key>WeatherPage</Key>
      <Title>Počasí</Title>
      <DisplayFilter>Guides</DisplayFilter>
      <Text>Planety sluneční soustavy nejsou tak klidné, jak se může zdát. Po sedmi dnech v jakémkoli světě s atmosférou se nevyzpytatelné síly přírody dostanou do akce - zasáhnou neopatrné Stationeery vánicemi, prachovými bouřkami a sopečnou činností.
ODA proto doporučuje, aby čerstvě nasazení Stationeerové vytvořili vzduchotěsnou základnu do 7 dnů od přistání.
Jakékoliv pohyblivé předměty ponechané venku v bouři - na Marsu, Loulanu, Vulkánu nebo Evropě - riskují, že budou odváty daleko, daleko, včetně vašeho přistávacího modulu.
Stejně tak si pamatujte, že solární panely jsou křehké a může se rozbít jejich sklo nebo občas dokonce zničit dostatečně zuřivou bouří. Během bouří se také drasticky snižuje jejich výkon.</Text>
    </StationpediaPage>
    <!--
    ~~~~~~~~~~~~~~~~~~~~~~~~~
    |                     TEMPLATES               |
    ~~~~~~~~~~~~~~~~~~~~~~~~~
    -->
    <StationpediaPage>
      <Key>ThingTemplate</Key>
      <Text>{0}

{HEADER:Všeobecné}
{LIST}Prefabrikovaný hash {POS:300}{1}
Malovatelné {POS:300}{2}{3}{/LIST}</Text>
    </StationpediaPage>
    <StationpediaPage>
      <Key>ThingThermalTemplate</Key>
      <Text>{HEADER:Tepelné limity}
{LIST}Rozbití {POS:300}{0}
Bod vzplanutí {POS:300}{1}
Samovznícení {POS:300}{2}{3}{/LIST}</Text>
    </StationpediaPage>
    <StationpediaPage>
      <Key>ThingSlotItemTemplate</Key>
      <Text>{0}. {1} Typ {2}</Text>
    </StationpediaPage>
    <StationpediaPage>
      <Key>ThingTransmissibleTemplate</Key>
      <Text>Připojí se k {POS:300}{THING:StructureLogicTransmitter}</Text>
    </StationpediaPage>
    <StationpediaPage>
      <Key>IceMeltingTemplate</Key>
      <Text>Teplota taveniny {1}
Tlak taveniny {0}</Text>
    </StationpediaPage>
    <StationpediaPage>
      <Key>ConstructedByHeaderTemplate</Key>
      <Text>{LIST}{0}{/LIST}</Text>
    </StationpediaPage>
    <StationpediaPage>
      <Key>CreatedHeaderTemplate</Key>
      <Text>{LIST}{0}{/LIST}</Text>
    </StationpediaPage>
    <StationpediaPage>
      <Key>ConstructedHeaderTemplate</Key>
      <Text>{LIST}{0}{/LIST}</Text>
    </StationpediaPage>
    <StationpediaPage>
      <Key>ReagentPageTemplate</Key>
      <Text>{LINK:ReagentPage;Činidlo}, často použitelné, když je ve formě {LINK:IngotPage;ingotů}.


{LIST}Unit {1}{/LIST}


{LIST}{2}{/LIST}</Text>
    </StationpediaPage>
    <StationpediaPage>
      <Key>GasPageTemplate</Key>
      <Text>{LINK:GasPage;Plyn}, který se často vytváří při {LINK:SmeltingPage;tavení}.


{LIST}Specifické teplo {1}{2}{/LIST}


{LIST}{0}{/LIST}</Text>
    </StationpediaPage>
    <StationpediaPage>
      <Key>GasPageFlamableTemplate</Key>
      <Text>Limit hořlavosti {0} až {1}</Text>
    </StationpediaPage>
    <StationpediaPage>
      <Key>NutritionPage</Key>
      <Title>Stationeerové nakonec dostanou hlad, ale ne všechno jídlo je stvořeno stejně. Míra hladu se také liší v závislosti na nastavení a obtížnosti. Stravování spotřebuje pouze tu část položky, která je adekvátní k obnovení hladu na 100%.

Stationeerové obdrží po příjezdu do nového světa zásoby potravin, například &lt;color=#0080FFFF&gt;{LINK:Agrizero;Agrizero}&lt;/color&gt; {THING:ItemCerealBar} v jejich přistávacím modulu. Když jsou vyčerpány, musíte najít nové zdroje obživy.

Konzumace syrových surovin uspokojí hlad méně než jídla, tj. Nahradí menší část vašeho hladu. Základní prvky jídla se vytvářejí pomocí systémů &lt;color=#0080FFFF&gt;{LINK:OrganicsPage;hydroponie}&lt;/color&gt;. Ty mohou být zpracovány na přísady receptů pomocí {THING:ApplianceReagentProcessor}, poté přeměněny na jídla pomocí {THING:ApplianceMicrowave}.

Míru hladu lze upravit v hlavní nabídce nastavení nastavením posuvníku Hlad / Hydratace.</Title>
      <DisplayFilter>Guides</DisplayFilter>
      <Text>Stationeerové nakonec dostanou hlad, ale ne všechno jídlo je stvořeno stejně. Míra hladu se také liší v závislosti na nastavení a obtížnosti. Stravování spotřebuje pouze tu část položky, která je adekvátní k obnovení hladu na 100%.

Stationeerové obdrží po příjezdu do nového světa zásoby potravin, například &lt;color=#0080FFFF&gt;{LINK:Agrizero;Agrizero}&lt;/color&gt; {THING:ItemCerealBar} v jejich přistávacím modulu. Když jsou vyčerpány, musíte najít nové zdroje obživy.

Konzumace syrových surovin uspokojí hlad méně než jídla, tj. Nahradí menší část vašeho hladu. Základní prvky jídla se vytvářejí pomocí systémů &lt;color=#0080FFFF&gt;{LINK:OrganicsPage;hydroponie}&lt;/color&gt;. Ty mohou být zpracovány na přísady receptů pomocí {THING:ApplianceReagentProcessor}, poté přeměněny na jídla pomocí {THING:ApplianceMicrowave}.

Míru hladu lze upravit v hlavní nabídce nastavení nastavením posuvníku Hlad / Hydratace.</Text>
    </StationpediaPage>
  </HelpPage>
</Language>
